.VERSION
AUTHORS.rst
CONTRIBUTING.rst
HISTORY.rst
LICENSE
MANIFEST.in
Pipfile
Pipfile.lock
README.rst
USAGE.rst
dev-requirements.txt
requirements.txt
setup.cfg
setup.py
docs/Makefile
docs/authors.rst
docs/conf.py
docs/contributing.rst
docs/history.rst
docs/index.rst
docs/installation.rst
docs/readme.rst
docs/usage.rst
tests/test_wikiseriesmarcblib.py
wikiseriesmarcblib/.VERSION
wikiseriesmarcblib/AUTHORS.rst
wikiseriesmarcblib/CONTRIBUTING.rst
wikiseriesmarcblib/HISTORY.rst
wikiseriesmarcblib/LICENSE
wikiseriesmarcblib/Pipfile
wikiseriesmarcblib/Pipfile.lock
wikiseriesmarcblib/README.rst
wikiseriesmarcblib/USAGE.rst
wikiseriesmarcblib/__init__.py
wikiseriesmarcblib/_version.py
wikiseriesmarcblib/dev-requirements.txt
wikiseriesmarcblib/requirements.txt
wikiseriesmarcblib/wikiseriesmarcblib.py
wikiseriesmarcblib/wikiseriesmarcblibexceptions.py
wikiseriesmarcblib.egg-info/PKG-INFO
wikiseriesmarcblib.egg-info/SOURCES.txt
wikiseriesmarcblib.egg-info/dependency_links.txt
wikiseriesmarcblib.egg-info/not-zip-safe
wikiseriesmarcblib.egg-info/requires.txt
wikiseriesmarcblib.egg-info/top_level.txt