Metadata-Version: 2.1
Name: wikiseriesmarcblib
Version: 0.1.0
Summary: Library to use wikipedia to query tv episodes list
Home-page: https://github.com/mmhvandenberg/wikiseriesmarcblib
Author: Marc van den Berg
Author-email: mmhvandenberg@outlook.com
License: MIT
Keywords: wikiseriesmarcblib tvseries
Classifier: Development Status :: 3 - Alpha
Classifier: Intended Audience :: Developers
Classifier: License :: OSI Approved :: MIT License
Classifier: Natural Language :: English
Classifier: Programming Language :: Python :: 3.9
License-File: LICENSE
License-File: AUTHORS.rst
